Workbook
Name GASTOS: #REF!
Name PPTO: #REF!

Sheet LISTA
A1: OBRA:
A3: Empresa:
C5: LISTADO DE PRECIO DE INSUMOS - Materiales y M.O.
E6: Fecha:
B7: CODIGO | C7: LISTA DE PRECIOS SIN IVA | D7: MARCA | E7: UN | F7: PRECIO
B8: 1 | C8: Jornal Básico Oficial | E8: Hs | F8: 631.9
B9: =B8+1 -> 2 | C9: Jornal Básico Ayudante | E9: Hs | F9: 197.07
B10: =B9+1 -> 3 | C10: Cemento | E10: Kg | F10: 6.15
B11: =B10+1 -> 4 | C11: Arena | E11: M3 | F11: 2890
B12: =B11+1 -> 5 | C12: Piedra | E12: M3 | F12: 3520
B13: =B12+1 -> 6 | C13: Hierro torsionado | E13: Kg | F13: 1562
B14: =B13+1 -> 7 | C14: Mallas sold. de Fe tors | E14: Kg | F14: 695.41
B15: =B14+1 -> 8 | C15: Alambre Negro | E15: Kg | F15: 298
B16: =B15+1 -> 9 | C16: Madera para encofrado | E16: M2 | F16: 478
B17: =B16+1 -> 10 | C17: Cal | E17: Kg | F17: 3.9
B18: =B17+1 -> 11 | C18: Ladrillo Cerámico 8x18x25 | E18: Nº | F18: 64.56
B19: =B18+1 -> 12 | C19: Hidrófugo | E19: Kg | F19: 1662
B20: =B19+1 -> 13 | C20: Techado asfaltico | E20: LTS | F20: 674.5
B21: =B20+1 -> 14 | C21: Pintura asfáltica | E21: Kg | F21: 1080
B22: =B21+1 -> 15
B23: =B22+1 -> 16 | C23: Metal desplegado | E23: Gl | F23: 418.85
B24: =B23+1 -> 17 | C24: Alambre galvanizado Nº 8 | E24: Kg | F24: 3055.32
B25: =B24+1 -> 18 | C25: Clavos | E25: Kg | F25: 360
B26: =B25+1 -> 19 | C26: Chapa Trapezoidal Nº 24 | E26: M2 | F26: 1738
B27: =B26+1 -> 20 | C27: Chapa Trap 1010 Nº 24 Prepintada | E27: M2 | F27: 890
B28: =B27+1 -> 21 | C28: Chapa AU L1 400 Nº 24 Galv | E28: M2 | F28: 1114
B29: =B28+1 -> 22 | C29: Correa de hierro Tipo C | E29: M2 | F29: 356.83
B30: =B29+1 -> 23 | C30: Viga metálica Tipo C | E30: M2 | F30: 13140
B31: =B30+1 -> 24 | C31: Chapa lisa Nº 24 Prepintada | E31: M2 | F31: 5500
B32: =B31+1 -> 25 | C32: Chapa lisa Nº 24 Galv | E32: M2 | F32: 6060
B33: =B32+1 -> 26 | C33: Cumbrera de Chº Nº 24 | E33: ML | F33: 2191
B34: =B33+1 -> 27 | C34: Gancho J P/techo | E34: Un | F34: 290
... B71: =B70+1 -> 64 | C71: Brea solida | E71: Kg | F71: 36
B72: =B71+1 -> 65 | C72: Cera | E72: Kg
B73: =B72+1 -> 66 | C73: Mosaico Granítico 30x30 Color | E73: M2 | F73: 100
B74: =B73+1 -> 67 | C74: Zócalo Granitico 10x30 | E74: Ml | F74: 380
B75: =B74+1 -> 68 | C75: Pastina color | E75: Kg | F75: 305.58
B76: =B75+1 -> 69 | C76: Losetas de 40x40 C/relieves | E76: Nº | F76: 190
B77: =B76+1 -> 70 | C77: Losetas de 50x40 Atermico p/borde | E77: Nº | F77: 412
B78: =B77+1 -> 71 | C78: Sellador de juntas en tiras | E78: Ml | F78: 375
B79: =B78+1 -> 72 | C79: Reja metálica | E79: Nº | F79: 540.76
B80: =B79+1 -> 73 | C80: Mortero de cto 1:3 | E80: M3 | F80: 1086
B81: =B80+1 -> 74 | C81: Machimbre de 3/4x4" | E81: M2 | F81: 400
B82: =B81+1 -> 75 | C82: Caballetes de pino 1 x 3 1/2" | E82: Ml | F82: 1000
B83: =B82+1 -> 76 | C83: Liston de pino 1/2 x 1 1/2" | E83: Ml | F83: 180
B84: =B83+1 -> 77 | C84: Alfajias de pino 1x3" | E84: Ml | F84: 30
... B98: =B97+1 -> 91 | C98: Perfil normal Nº 8 | E98: Kg | F98: 1200

Sheet ANALISIS DE PRECIOS
A1: OBRA:
A3: Empresa:
B5: ANALISIS DE COSTOS | U5: 333
A6: Fecha:
A8: Item: | B8: COSTO HORARIO DE LA MANO DE OBRA
A9: Unidad: | B9: (Hs)
L10: FEBRERO/2004 | M10: AGOSTO/2003
A11: A: OFICIAL ALBAÑIL
A12: Nº | B12: DESIGNACION | C12: UNIDAD | D12: CANTIDAD | E12: PRECIO | F12: PRECIO | J12: OFICIAL
E13: UNITARIO | F13: TOTAL
B14: Jornal Básico | D14: 1 | E14: =+LISTA!F8 -> 631.9 | F14: =ROUND(D14*E14,2) -> 631.9 | J14: BASICO | L14: =+F14 -> 631.9 | M14: 1.56
B15: Asistencia Perfecta | D15: 0.18 | E15: =+E14 -> 631.9 | F15: =ROUND(D15*E15,2) -> 113.74 | J15: ASISTENCIA PERFECTA | K15: 0.18 | L15: =+L14*K15 -> 113.742 | M15: =+M14*K15 -> 0.2808
B16: PARCIAL | F16: =+F14+F15 -> 745.64 | J16: PARCIAL | L16: =+L14+L15 -> 745.642 | M16: =+M14+M15 -> 1.8408
B17: Cargas sociales | D17: 0.58 | E17: =+F16 -> 745.64 | F17: =ROUND(D17*E17,2) -> 432.47 | J17: FONDO DESEMPLEO | K17: 0.12 | L17: =+$K17*$L$16 -> 89.47704 | M17: =+$K17*$M$16 -> 0.220896
B18: Seguro Obrero | D18: 0.0766 | E18: =E17 -> 745.64 | F18: =ROUND(D18*E18,2) -> 57.12 | J18: ART | K18: 0.0766 | L18: =+$K18*$L$16 -> 57.116177 | M18: =+$K18*$M$16 -> 0.14100528
B19: Ley Provincial 49 | D19: 0.005 | E19: =E18 -> 745.64 | F19: =ROUND(D19*E19,2) -> 3.73 | J19: APORTE PATRONAL JUBILACION | K19: 0.17 | L19: =+$K19*$L$16 -> 126.75914 | M19: =+$K19*$M$16 -> 0.312936
J20: OSPECON | K20: 0.06 | L20: =+$K20*$L$16 -> 44.73852 | M20: =+$K20*$M$16 -> 0.110448
F21: =SUM(F16:F19) -> 1238.96 | J21: CAUSAS CLIMATICAS | K21: 0.008 | L21: =+$K21*$L$16 -> 5.965136 | M21: =+$K21*$M$16 -> 0.0147264
C22: TOTAL | F22: =+F21 -> 1238.96 | J22: FONDO SALUD PUBLICA | K22: 0.005 | L22: =+$K22*$L$16 -> 3.72821 | M22: =+$K22*$M$16 -> 0.009204
J23: ENFERMEDAD | K23: 0.029 | L23: =+$K23*$L$16 -> 21.623618 | M23: =+$K23*$M$16 -> 0.0533832
J24: VACACIONES | K24: 0.0622 | L24: =+$K24*$L$16 -> 46.378932 | M24: =+$K24*$M$16 -> 0.11449776
A25: Item: | B25: COSTO HORARIO DE LA MANO DE OBRA | J25: S.A.C. | K25: 0.1112 | L25: =+$K25*$L$16 -> 82.91539 | M25: =+$K25*$M$16 -> 0.20469696
A26: Unidad: | B26: (Hs) | J26: VESTIMENTA | K26: 0.018 | L26: =+$K26*$L$16 -> 13.421556 | M26: =+$K26*$M$16 -> 0.0331344
J27: FERIADOS | K27: 0.002 | L27: =+$K27*$L$16 -> 1.491284 | M27: =+$K27*$M$16 -> 0.0036816
A28: B: AYUDANTE ALBAÑIL | J28: JORNAL DE APLICACION | L28: =SUM(L16:L27) -> 1239.257 | M28: =SUM(M16:M27) -> 3.0594096
A29: Nº | B29: DESIGNACION | C29: UNIDAD | D29: CANTIDAD | E29: PRECIO | F29: PRECIO | J29: FACTOR | L29: =+L28/L16 -> 1.662 | M29: =150/176 -> 0.85227273
E30: UNITARIO | F30: TOTAL | M30: =+M28+M29 -> 3.9116823 | N30: =+L28/M30 -> 316.80921
B31: Jornal Básico | D31: 1 | E31: =+LISTA!F9 -> 197.07 | F31: =ROUND(D31*E31,2) -> 197.07
B32: Asistencia Perfecta | D32: 0.18 | E32: =+E31 -> 197.07 | F32: =ROUND(D32*E32,2) -> 35.47
B33: PARCIAL | F33: =+F31+F32 -> 232.54 | J33: AYUDANTE
B34: Cargas sociales | D34: 0.58 | E34: =+F33 -> 232.54 | F34: =ROUND(D34*E34,2) -> 134.87
B35: Seguro Obrero | D35: 0.0766 | E35: =E34 -> 232.54 | F35: =ROUND(D35*E35,2) -> 17.81 | J35: BASICO | L35: =+F31 -> 197.07 | M35: 1.48
B36: Ley Provincial 49 | D36: 0.005 | E36: =E35 -> 232.54 | F36: =ROUND(D36*E36,2) -> 1.16 | J36: ASISTENCIA PERFECTA | K36: =+K15 -> 0.18 | L36: =+L35*K36 -> 35.4726 | M36: =+M35*K36 -> 0.2664
J37: PARCIAL | K37: =+K16 -> 0 | L37: =+L35+L36 -> 232.5426 | M37: =+M35+M36 -> 1.7464
F38: =SUM(F33:F37) -> 386.38 | J38: FONDO DESEMPLEO | K38: =+K17 -> 0.12 | L38: =+$K38*$L$37 -> 27.905112 | M38: =+$K38*$M$37 -> 0.209568
C39: TOTAL | F39: =+F38 -> 386.38 | J39: ART | K39: =+K18 -> 0.0766 | L39: =+$K39*$L$37 -> 17.812763 | M39: =+$K39*$M$37 -> 0.13377424
J40: APORTE PATRONAL JUBILACION | K40: =+K19 -> 0.17 | L40: =+$K40*$L$37 -> 39.532242 | M40: =+$K40*$M$37 -> 0.296888
A41: Item: | B41: LIMPIEZA Y NIVELACION DEL TERRENO | J41: OSPECON | K41: =+K20 -> 0.06 | L41: =+$K41*$L$37 -> 13.952556 | M41: =+$K41*$M$37 -> 0.104784
A42: Unidad: | B42: (GL) | J42: CAUSAS CLIMATICAS | K42: =+K21 -> 0.008 | L42: =+$K42*$L$37 -> 1.8603408 | M42: =+$K42*$M$37 -> 0.0139712
J43: FONDO SALUD PUBLICA | K43: =+K22 -> 0.005 | L43: =+$K43*$L$37 -> 1.162713 | M43: =+$K43*$M$37 -> 0.008732
A44: A: M A T E R I A L E S | J44: ENFERMEDAD | K44: =+K23 -> 0.029 | L44: =+$K44*$L$37 -> 6.7437354 | M44: =+$K44*$M$37 -> 0.0506456
A45: Nº | B45: DESIGNACION | C45: UNIDAD | D45: CANTIDAD | E45: PRECIO | F45: PRECIO | J45: VACACIONES | K45: =+K24 -> 0.0622 | L45: =+$K45*$L$37 -> 14.46415 | M45: =+$K45*$M$37 -> 0.10862608
E46: UNITARIO | F46: TOTAL | J46: S.A.C. | K46: =+K25 -> 0.1112 | L46: =+$K46*$L$37 -> 25.858737 | M46: =+$K46*$M$37 -> 0.19419968
B47: Alq. Equipos Retroexcavadora | C47: GL | D47: 80 | E47: 40 | F47: =ROUND(D47*E47,2) -> 3200 | J47: VESTIMENTA | K47: =+K26 -> 0.018 | L47: =+$K47*$L$37 -> 4.1857668 | M47: =+$K47*$M$37 -> 0.0314352
B48: Alq. Equipos Camiones | C48: GL | D48: 80 | E48: 80 | F48: =ROUND(D48*E48,2) -> 6400 | J48: FERIADOS | K48: =+K27 -> 0.002 | L48: =+$K48*$L$37 -> 0.4650852 | M48: =+$K48*$M$37 -> 0.0034928
J49: JORNAL DE APLICACION | L49: =SUM(L37:L48) -> 386.4858 | M49: =SUM(M37:M48) -> 2.9025168
D50: SUBTOTAL 1 | G50: =SUM(F47:F49) -> 9600 | J50: FACTOR | L50: =+L49/L37 -> 1.662 | M50: =150/176 -> 0.85227273 | N50: =+M49/M35 -> 1.96116
M51: =+M49+M50 -> 3.7547895 | N51: =+L49/M51 -> 102.93142
A52: B: M A N O DE O B R A
A53: Nº | B53: DESIGNACION | C53: UNIDAD | D53: CANTIDAD | E53: PRECIO | F53: PRECIO
E54: UNITARIO | F54: TOTAL
B55: Oficial | C55: hs | D55: 80 | E55: =+$F$22 -> 1238.96 | F55: =ROUND(D55*E55,2) -> 99116.8
B56: Ayudante | C56: hs | D56: 160 | E56: =+$F$39 -> 386.38 | F56: =ROUND(D56*E56,2) -> 61820.8
D57: SUBTOTAL 2 | G57: =SUM(F55:F56) -> 160937.6
D59: TOTAL DEL ITEM | G59: =SUM(G50:G57) -> 170537.6
A61: Item: | B61: DESMALEZAMIENTO del TERRENO
A62: Unidad: | B62: M2
A64: A: M A T E R I A L E S
A65: Nº | B65: DESIGNACION | C65: UNIDAD | D65: CANTIDAD | E65: PRECIO | F65: PRECIO
E66: UNITARIO | F66: TOTAL
D70: SUBTOTAL 1 | G70: =SUM(F67:F69) -> 0
A72: B: M A N O DE O B R A
A73: Nº | B73: DESIGNACION | C73: UNIDAD | D73: CANTIDAD | E73: PRECIO | F73: PRECIO
E74: UNITARIO | F74: TOTAL
B75: Oficial | C75: hs | D75: 0 | E75: =+$F$22 -> 1238.96 | F75: =ROUND(D75*E75,2) -> 0
B76: Ayudante | C76: hs | D76: 0.01 | E76: =+$F$39 -> 386.38 | F76: =ROUND(D76*E76,2) -> 3.86
D77: SUBTOTAL 2 | G77: =SUM(F75:F76) -> 3.86
D79: TOTAL DEL ITEM | G79: =SUM(G70:G77) -> 3.86
E81: carpinteria | G81: =+G79*300 -> 1158
A82: Item: | B82: CARTEL DE OBRA
A83: Unidad: | B83: (GL)
A85: A: M A T E R I A L E S
A86: Nº | B86: DESIGNACION | C86: UNIDAD | D86: CANTIDAD | E86: PRECIO | F86: PRECIO
E87: UNITARIO | F87: TOTAL
B88: Tubos estructurales metálicos | C88: KG | D88: 60 | E88: 0.9 | F88: =ROUND(D88*E88,2) -> 54
B89: Chapa H°N° Nº 18 | C89: Kg | D89: 80 | E89: 0.828 | F89: =ROUND(D89*E89,2) -> 66.24
B90: Electrodos | C90: KG | D90: 4 | E90: 2.8 | F90: =ROUND(D90*E90,2) -> 11.2
B91: Antióxido | C91: Lts | D91: 4 | E91: 3 | F91: =ROUND(D91*E91,2) -> 12
B92: Esmalte sintético | C92: Lts | D92: 4 | E92: 4.1949153 | F92: =ROUND(D92*E92,2) -> 16.78
D93: SUBTOTAL 1 | G93: =SUM(F88:F92) -> 160.22
A95: B: M A N O DE O B R A
A96: Nº | B96: DESIGNACION | C96: UNIDAD | D96: CANTIDAD | E96: PRECIO | F96: PRECIO
E97: UNITARIO | F97: TOTAL
B98: Oficial Herrero | C98: hs | D98: 20 | E98: =+$F$22*1.2 -> 1486.752 | F98: =ROUND(D98*E98,2) -> 29735.04
B99: Letrista | C99: hs | D99: 20 | E99: =+$F$22*1.2 -> 1486.752 | F99: =ROUND(D99*E99,2) -> 29735.04
B100: Oficial | C100: hs | D100: 4 | E100: =+$F$22 -> 1238.96 | F100: =ROUND(D100*E100,2) -> 4955.84
B101: Ayudante | C101: hs | D101: 8 | E101: =+$F$39 -> 386.38 | F101: =ROUND(D101*E101,2) -> 3091.04
D102: SUBTOTAL 2 | G102: =SUM(F98:F101) -> 67516.96
D104: TOTAL DEL ITEM | G104: =SUM(G92:G102) -> 67677.18
A106: Item: | B106: OBRADOR
A107: Unidad: | B107: (GL)
A109: A: M A T E R I A L E S
A110: Nº | B110: DESIGNACION | C110: UNIDAD | D110: CANTIDAD | E110: PRECIO | F110: PRECIO
E111: UNITARIO | F111: TOTAL
B112: Adecuar instalaciones p/obrador | C112: Gl | D112: 1 | E112: 250 | F112: =ROUND(D112*E112,2) -> 250
B113: Instalaciones | C113: Gl | D113: 1 | E113: 200 | F113: =ROUND(D113*E113,2) -> 200
B114: Obrador | C114: Gl | D114: 1 | E114: 5250 | F114: =ROUND(D114*E114,2) -> 5250
D115: SUBTOTAL 1 | G115: =SUM(F112:F114) -> 5700
A117: B: M A N O DE O B R A
A118: Nº | B118: DESIGNACION | C118: UNIDAD | D118: CANTIDAD | E118: PRECIO | F118: PRECIO
...

Sheet Computo
A1: Computo de obra
A2: Segovia Joaquin Ezequiel
A4: RUBROS | B4: Designacion | E4: N° de partes | G4: Largo | H4: Ancho | I4: Altura | J4: Unidad | K4: Parcial | L4: Total
A5: 1 | B5: EXCAVACIONES
A6: 1.1 | B6: Exc. de V.Encadenado inferior | L6: 38.351358
A7: 1.2 | B7: V.E.1 | E7: 1 | G7: 6 | H7: 0.2 | I7: 0.2 | J7: m3 | K7: =G7*H7*I7 -> 0.24
A8: 1.3 | B8: V.E.2 | E8: 3 | G8: 3 | H8: 0.2 | I8: 0.2 | J8: m3 | K8: =G8*H8*I8 -> 0.12
A9: 1.4 | B9: V.E.3 | E9: 3 | G9: 4 | H9: 0.2 | I9: 0.2 | J9: m3 | K9: =G9*H9*I9 -> 0.16
A10: 1.5 | B10: V.E.4 | E10: 2 | G10: 20.7 | H10: 0.2 | I10: 0.2 | J10: m3 | K10: =G10*H10*I10 -> 0.828
A11: 1.6 | B11: V.E.5 | E11: 1 | G11: 12 | H11: 0.2 | I11: 0.2 | J11: m3 | K11: =G11*H11*I11 -> 0.48
A12: 1.7 | B12: V.E.6 | E12: 6 | G12: 3.4 | H12: 0.2 | I12: 0.2 | J12: m3 | K12: =G12*H12*I12 -> 0.136
A13: 1.8 | B13: V.E.7 | E13: 3 | G13: 2.4 | H13: 0.2 | I13: 0.2 | J13: m3 | K13: =G13*H13*I13 -> 0.096
A14: 1.9 | B14: V.E.8 | E14: 3 | G14: 2.2 | H14: 0.2 | I14: 0.2 | J14: m3 | K14: =G14*H14*I14 -> 0.088
A15: 2 | B15: V.E.9 | E15: 4 | G15: 2.8 | H15: 0.2 | I15: 0.2 | J15: m3 | K15: =G15*H15*I15 -> 0.112
A16: 2.1 | B16: V.E.10 | E16: 2 | G16: 3.5 | H16: 0.2 | I16: 0.2 | J16: m3 | K16: =G16*H16*I16 -> 0.14
A17: 2.2 | B17: V.E.11 | E17: 2 | G17: 5.1 | H17: 0.2 | I17: 0.2 | J17: m3 | K17: =G17*H17*I17 -> 0.204
A18: 2.3 | B18: V.E.12 | E18: 2 | G18: 1.9 | H18: 0.2 | I18: 0.2 | J18: m3 | K18: =G18*H18*I18 -> 0.076
A19: 2.4 | B19: V.E.13 | E19: 1 | G19: 3.1 | H19: 0.2 | I19: 0.2 | J19: m3 | K19: =G19*H19*I19 -> 0.124
A20: 2.5 | B20: V.E.14 | E20: 1 | G20: 3.8 | H20: 0.2 | I20: 0.2 | J20: m3 | K20: =G20*H20*I20 -> 0.152 | L20: =K7+K8+K9+K10+K11+K12+K13+K14+K15+K16+K17+K18+K19+K20 -> 2.956 | N20: =SUM(E7:E20) -> 34 | P20: =N20*L20 -> 100.504
A21: 2.6 | B21: Exc. de pilotines | E21: 137 | H21: 0.0314 | I21: 1.31 | J21: m3 | K21: =E21*H21*I21 -> 5.635358 | L21: =K21 -> 5.635358
A22: 2.7 | B22: Exc. de Zapatas aisladas 2 | E22: 22 | G22: 0.8 | H22: 0.8 | I22: 1.5 | J22: m3 | K22: =G22*H22*I22*E22 -> 21.12
A23: 2.8 | B23: Exc. de Zaptas aisladas 1 | E23: 4 | G23: 1.2 | H23: 1.2 | I23: 1.5 | J23: m3 | K23: =G23*H23*I23*E23 -> 8.64 | L23: =K22+K23 -> 29.76
A24: 2.9 | B24: HORMIGON ARMADO | L24: =K33+K25+K26+K27+K28+K29+K30 -> 366.21269
A25: 3 | B25: H°A° Viga de encadenado inf. | E25: tomar igual valor para excavacion | J25: m3 | K25: =L20 -> 2.956
A26: 3.1 | B26: H°A° para pilotines | E26: tomar igual valor para excavacion | J26: m3 | K26: =K21 -> 5.635358
A27: 3.2 | B27: H°A° para fondos 1 | E27: 2 | G27: 1.2 | H27: 1.2 | I27: 0.2 | J27: m3 | K27: =G27*H27*I27*E27 -> 0.576 | L27: =K27+K29 -> 0.832
A28: 3.3 | B28: H°A° para piramidal 1 | E28: 2 | G28: 1.2 | H28: 1.2 | I28: 0.1166667 | J28: m3 | K28: =G28*H28*I28*E28 -> 0.3360001 | L28: =K28+K30 -> 0.48533347
A29: 3.4 | B29: H°A° para fondos 2 | E29: 2 | G29: 0.8 | H29: 0.8 | I29: 0.2 | J29: m3 | K29: =G29*H29*I29*E29 -> 0.256
A30: 3.5 | B30: H°A° para piramidal 2 | E30: 2 | G30: 0.8 | H30: 0.8 | I30: 0.1166667 | J30: m3 | K30: =G30*H30*I30*E30 -> 0.14933338
A31: 3.6 | B31: H°A° para columnas
A32: 3.7 | B32: H°A° para vigas
A33: 3.8 | B33: H°A° para losas | E33: 1 | G33: 57.1 | H33: 31.2 | I33: 0.2 | J33: m3 | K33: =G33*H33*I33 -> 356.304
A34: 3.9
A35: 4 | B35: MAMPOSTERIA
A36: 4.1 | B36: Mamposteria L.C 0.20 cm | L36: =K37+K38+K39+K40+K41+K42+K43+K44+K45+K46+K47+K41+K49+K50+K51+K52+K53+K54 -> 165.532
A37: 4.2 | B37: Pared 1 | E37: 4 | G37: 13.7 | H37: 0.2 | I37: 3 | J37: m3 | K37: =G37*H37*I37*E37 -> 32.88
A38: 4.3 | B38: Pared 2 | E38: 3 | G38: 11.6 | H38: 0.2 | I38: 3 | J38: m3 | K38: =G38*H38*I38*E38 -> 20.88
A39: 4.4 | B39: Pared 3 | E39: 1 | G39: 7.5 | H39: 0.2 | I39: 3 | J39: m3 | K39: =G39*H39*I39 -> 4.5
A40: 4.5 | B40: Pared 4 | E40: 1 | G40: 5.5 | H40: 0.2 | I40: 3 | J40: m3 | K40: =G40*H40*I40 -> 3.3
A41: 4.6 | B41: Pared 5 | E41: 9 | G41: 3.4 | H41: 0.2 | I41: 3 | J41: m3 | K41: =G41*H41*I41*E41 -> 18.36
A42: 4.7 | B42: Pared 6 | E42: 6 | G42: 2.3 | H42: 0.2 | I42: 3 | J42: m3 | K42: =G42*H42*I42*E42 -> 8.28
A43: 4.8 | B43: Pared 7 | E43: 1 | G43: 1.1 | H43: 0.2 | I43: 3 | J43: m3 | K43: =G43*H43*I43*E43 -> 0.66
A44: 4.9 | B44: Pared 8 | E44: 1 | G44: 1.7 | H44: 0.2 | I44: 3 | J44: m3 | K44: =G44*H44*I44*E44 -> 1.02
A45: 5 | B45: Pared 9 | E45: 2 | G45: 5 | H45: 0.2 | I45: 3 | J45: m3 | K45: =G45*H45*I45*E45 -> 6
A46: 5.1 | B46: Pared 10 | E46: 3 | G46: 0.9 | H46: 0.2 | I46: 3 | J46: m3 | K46: =G46*H46*I46*E46 -> 1.62
A47: 5.2 | B47: pared 11 | E47: 2 | G47: 5.5 | H47: 0.2 | I47: 5.3 | J47: m3 | K47: =G47*H47*I47*E47 -> 11.66
A48: 5.3 | B48: pared 12 | E48: 2 | G48: 6 | H48: 0.2 | I48: 3 | J48: m3 | K48: =G48*H48*I48*E48 -> 7.2
A49: 5.4 | B49: pared 13 | E49: 1 | G49: 6.4 | H49: 0.2 | I49: 3 | J49: m3 | K49: =G49*H49*I49*E49 -> 3.84
A50: 5.5 | B50: pared 14 | E50: 1 | G50: 4.4 | H50: 0.2 | I50: 3 | J50: m3 | K50: =G50*H50*I50*E50 -> 2.64
A51: 5.6 | B51: pared 15 | E51: 1 | G51: 4 | H51: 0.2 | I51: 3 | J51: m3 | K51: =G51*H51*I51*E51 -> 2.4
A52: 5.7 | B52: pared 16 | E52: 1 | G52: 3.1 | H52: 0.2 | I52: 5.3 | J52: m3 | K52: =G52*H52*I52*E52 -> 3.286
... A54: 5.9 | B54: pared 18 | E54: 2 | G54: 20.9 | H54: 0.2 | I54: 2.8 | J54: m3 | K54: =G54*H54*I54*E54 -> 23.408
A55: 6 | B55: Mamposteria L.C 0.15cm | L55: =K56+K57+K58+K59 -> 2.475
A56: 6.1 | B56: pared 1 | E56: 1 | G56: 1 | H56: 0.15 | I56: 3 | J56: m3 | K56: =G56*H56*I56*E56 -> 0.45
A57: 6.2 | B57: pared 2 | E57: 1 | G57: 1.5 | H57: 0.15 | I57: 3 | J57: m3 | K57: =G57*H57*I57*E57 -> 0.675
A58: 6.3 | B58: pared 3 | E58: 2 | G58: 0.8 | H58: 0.15 | I58: 3 | J58: m3 | K58: =G58*H58*I58*E58 -> 0.72
A59: 6.4 | B59: pared4 | E59: 1 | G59: 1.4 | H59: 0.15 | I59: 3 | J59: m3 | K59: =G59*H59*I59*E59 -> 0.63
A60: 6.5
A61: 6.6
A62: 6.7. | B62: CAPA AISLADORA DOBLE SELLADA | L62: =K63+K64 -> 0.37343972 | O62: =+O63+O64 -> 85.0245
A63: 6.8 | B63: capa aisladora muro 0.20 | G63: 74.82 | H63: 0.2 | I63: 0.35 | J63: m3 | K63: =H63*I63*H63*I63*G63 -> 0.366618 | N63: =0.35+0.35+0.4 -> 1.1 | O63: =+G63*N63 -> 82.302
A64: 6.9 | B64: capa aisladora muro 0.15 | G64: 2.475 | H64: 0.15 | I64: 0.35 | J64: m3 | K64: =H64*I64*H64*I64*G64 -> 0.0068217188 | N64: =0.35+0.35+0.4 -> 1.1 | O64: =+G64*N64 -> 2.7225
A65: 7 | B65: CONTRAPISO
A66: 7.1 | B66: contrapiso sobre terreno natural | L66: =K67+K68+K69+K70+K71+K72+K73+K74 -> 212.5
A67: 7.2 | B67: Local N°1 | G67: 7.2 | H67: 8.1 | J67: m2 | K67: =G67*H67 -> 58.32
A68: 7.3 | B68: Local N°2 | G68: 4 | H68: 3.4 | J68: m2 | K68: =G68*H68 -> 13.6
A69: 7.4 | B69: Local N°3 | G69: 6 | H69: 3.4 | J69: m2 | K69: =G69*H69 -> 20.4
A70: 7.5 | B70: Local N°4 | G70: 6 | H70: 2.3 | J70: m2 | K70: =G70*H70 -> 13.8
A71: 7.6 | B71: Local N°5 | G71: 5.5 | H71: 4.2 | J71: m2 | K71: =G71*H71 -> 23.1
A72: 7.7 | B72: Local N° 6 | G72: 6.2 | H72: 5.1 | J72: m2 | K72: =G72*H72 -> 31.62
A73: 7.8 | B73: Local N°7 | G73: 8.2 | H73: 3.9 | J73: m2 | K73: =G73*H73 -> 31.98
A74: 7.9 | B74: Local N°8 | G74: 8.2 | H74: 2.4 | J74: m2 | K74: =G74*H74 -> 19.68
A75: 8 | B75: PISO
A76: 8.1 | B76: Ceramico 30x30 | L76: =L66 -> 212.5
A77: 8.2 | B77: ZOCALO
A78: 8.3 | B78: zocalo ceramico 50x50 | C78: 30x30 | L78: =K79 -> 184.3
A79: 8.4 | B79: zocalo ceramico int. | G79: 184.3 | J79: ml | K79: 184.3
A80: 8.5 | B80: REVOQUE
A81: 8.6 | B81: Revoque exterior completo | L81: =K82+K84+K85+K86+K87+K89+K90+K91+K92+K93+K94+K95+K96+K97+K98+K88+K83 -> 483.94
A82: 8.7 | B82: Pared 1 | E82: 2 | G82: 13.9 | I82: 3 | J82: m2 | K82: =G82*I82*E82 -> 83.4
A83: 8.8 | B83: Pared 2 | E83: 1 | G83: 11.6 | I83: 3 | J83: m2 | K83: =G83*I83*E83 -> 34.8
A84: 8.9 | B84: Pared 3 | E84: 1 | G84: 5.5 | I84: 3 | J84: m2 | K84: =G84*I84*E84 -> 16.5
A85: 9 | B85: Pared 4 | E85: 3 | G85: 6.2 | I85: 3 | J85: m2 | K85: =G85*I85*E85 -> 55.8
A86: 9.1 | B86: Pared 5 | E86: 2 | G86: 5.7 | I86: 3 | J86: m2 | K86: =G86*I86*E86 -> 34.2
A87: 9.2 | B87: Pared 6 | E87: 2 | G87: 4.2 | I87: 3 | J87: m2 | K87: =G87*I87*E87 -> 25.2
A88: 9.3 | B88: Pared 7 | E88: 3 | G88: 2.3 | I88: 3 | J88: m2 | K88: =G88*I88*E88 -> 20.7
A89: 9.4 | B89: Pared 8 | E89: 2 | G89: 1.2 | I89: 3 | J89: m2 | K89: =G89*I89*E89 -> 7.2
A90: 9.5 | B90: Pared 9 | E90: 1 | G90: 5.7 | I90: 5.3 | J90: m2 | K90: =G90*I90*E90 -> 30.21
A91: 9.6 | B91: Pared 10 | E91: 1 | G91: 7.5 | I91: 5.3 | J91: m2 | K91: =G91*I91*E91 -> 39.75
A92: 9.7 | B92: Pared 11 | E92: 1 | G92: 8.7 | I92: 3 | J92: m2 | K92: =G92*I92*E92 -> 26.1
A93: 9.8 | B93: Pared 12 | E93: 1 | G93: 3.1 | I93: 5.3 | J93: m2 | K93: =G93*I93*E93 -> 16.43
... A98: 10.3 | B98: Pared 17 | E98: 2 | G98: 1.7 | I98: 3 | J98: m2 | K98: =G98*I98*E98 -> 10.2
A99: 10.4 | B99: Revoque interior completo | L99: =K100+K101+K102+K103+K104+K105+K106+K108+K107+K109+K111+K110+K112+K113+K114+K115+K116+K117+K118+K119+K120 -> 656.8
A100: 10.5 | B100: Pared 1 | E100: 3 | G100: 7.2 | I100: 3 | J100: m2 | K100: =G100*I100*E100 -> 64.8
A101: 10.6 | B101: Pared 2 | E101: 1 | G101: 5.5 | I101: 3 | J101: m2 | K101: =G101*I101*E101 -> 16.5
A102: 10.7 | B102: Pared 3 | E102: 1 | G102: 8 | I102: 3 | J102: m2 | K102: =G102*I102*E102 -> 24
A103: 10.8 | B103: Pared 4 | E103: 1 | G103: 3.2 | I103: 3 | J103: m2 | K103: =G103*I103*E103 -> 9.6
A104: 10.9 | B104: Pared 5 | E104: 1 | G104: 1.9 | I104: 3 | J104: m2 | K104: =G104*I104*E104 -> 5.7
A105: 11 | B105: Pared 6 | E105: 2 | G105: 1.7 | I105: 3 | J105: m2 | K105: =G105*I105*E105 -> 10.2
A106: 11.1 | B106: Pared 7 | E106: 1 | G106: 13.7 | I106: 3 | J106: m2 | K106: =G106*I106*E106 -> 41.1
...

Sheet Presupuesto
C2: OBRA:
C4: Empresa:
D6: PLANILLA de COMPUTO y PRESUPUESTO
H8: Fecha:
C10: Nº | D10: DESIGNACION DE LAS OBRAS | E10: UNIDAD | F10: CANTIDAD | G10: PRECIO | H10: IMPORTE | J10: %
F11: TOTAL | G11: UNITARIO | H11: PARCIAL | I11: TOTAL | J11: INCIDENCIA
C12: 1 | D12: EXCAVACION | I12: =H13+H14+H15 -> 115884.92
C13: 1.1 | D13: Exc viga de encadenado inferior | E13: m3 | F13: =+Computo!L20 -> 2.956 | G13: =+'ANALISIS DE PRECIOS'!G203 -> 1545.52 | H13: =+F13*G13 -> 4568.5571
C14: 1.2 | D14: Exc para pilotines | E14: m3 | F14: =+Computo!L21 -> 5.635358 | G14: =+'ANALISIS DE PRECIOS'!G222 -> 11591.4 | H14: =+F14*G14 -> 65321.689
C15: 1.3 | D15: Exc para zapatas aisladas | E15: m3 | F15: =+Computo!L23 -> 29.76 | G15: =+'ANALISIS DE PRECIOS'!G203 -> 1545.52 | H15: =+F15*G15 -> 45994.675
C16: 1.4 | D16: HORMIGON ARMADO | I16: =H17+H21+H22+H18 -> 1716684.6
C17: 1.5 | D17: H°A° Viga encadenado inf | E17: m3 | F17: =+Computo!K25 -> 2.956 | G17: =+'ANALISIS DE PRECIOS'!G290 -> 160846.1 | H17: =+F17*G17 -> 475461.07
C18: 1.6 | D18: H°A° para pilotines | E18: m3 | F18: =+Computo!K26 -> 5.635358 | G18: =+'ANALISIS DE PRECIOS'!G244 -> 152259.5 | H18: =+F18*G18 -> 858036.79
C19: 1.7 | D19: H°A°para fondos | E19: m3 | F19: =+Computo!L27 -> 0.832
C20: 1.8 | D20: H°A° para piramidal | E20: m3 | F20: =+Computo!L28 -> 0.48533347
C21: 1.9 | D21: H°A° para columnas | E21: m3 | G21: =+'ANALISIS DE PRECIOS'!G267 -> 222340.6 | H21: =+G21 -> 222340.6
C22: 2 | D22: H°A° para vigas | E22: m3 | G22: =+'ANALISIS DE PRECIOS'!G290 -> 160846.1 | H22: =+G22 -> 160846.1
C23: 2.1 | D23: H°A° para losa | E23: m3 | F23: =+Computo!K33 -> 356.304
C24: 2.2 | D24: MAMPOSTERIA | I24: =+H25+H26 -> 3530704.5
C25: 2.3 | D25: Mamposteria de ladrillo comun ext 0.20m | E25: m3 | F25: =+Computo!L36 -> 165.532 | G25: =+'ANALISIS DE PRECIOS'!G330 -> 19721.05 | H25: =+F25*G25 -> 3264464.8
C26: 2.4 | D26: Mamposteria de ladrillo comun 0.15m | E26: m3 | F26: =+Computo!L55 -> 2.475 | G26: =+'ANALISIS DE PRECIOS'!G374 -> 107571.57 | H26: =+F26*G26 -> 266239.64
C27: 2.5 | D27: CAPA AISLADORA DOBLE SELLADA | I27: =+H28 -> 237873.04
C28: 2.6 | D28: CAPA AISLADORA DOBLE SELLADA | E28: m2 | F28: =+Computo!O62 -> 85.0245 | G28: =+'ANALISIS DE PRECIOS'!G458 -> 2797.7 | H28: =+F28*G28 -> 237873.04
C29: 2.7
C30: 2.8 | D30: CONTRAPISO | I30: =+H31 -> 366692.12
C31: 2.9 | D31: Locales | E31: m2 | F31: =+Computo!L66 -> 212.5 | G31: =+'ANALISIS DE PRECIOS'!G771 -> 1725.61 | H31: =+F31*G31 -> 366692.12
C32: 3 | D32: PISO | I32: =+H33 -> 690737.62
C33: 3.1 | D33: Ceramico 30x30 | E33: m2 | F33: =+Computo!L76 -> 212.5 | G33: =+'ANALISIS DE PRECIOS'!G838 -> 3250.53 | H33: =+F33*G33 -> 690737.62
C34: 3.2 | D34: ZOCALO | I34: =+H35 -> 190831.59
C35: 3.3 | D35: Zocalo 30x30 | E35: ml | F35: =+Computo!L78 -> 184.3 | G35: =+'ANALISIS DE PRECIOS'!G926 -> 1035.44 | H35: =+F35*G35 -> 190831.59
C36: 3.4 | D36: REVOQUE | I36: =+H37+H38 -> 4544660.1
C37: 3.5 | D37: Revoque exterior completo | E37: m2 | F37: =+Computo!L81 -> 483.94 | G37: =+'ANALISIS DE PRECIOS'!G602 -> 7637.03 | H37: =+F37*G37 -> 3695864.3
C38: 3.6 | D38: Revoque interior completo | E38: m2 | F38: =+Computo!L99 -> 656.8 | G38: =+'ANALISIS DE PRECIOS'!G558 -> 1292.32 | H38: =+F38*G38 -> 848795.78
C39: 3.7 | D39: PINTURA | I39: =+H40+H41+H44+H45 -> 2501163.4
C40: 3.8 | D40: Pintura latex exterior | E40: m2 | F40: =+Computo!K122 -> 483.94 | G40: =+'ANALISIS DE PRECIOS'!G1089 -> 2561.25 | H40: =+F40*G40 -> 1239491.3
C41: 3.9 | D41: Pintura latex interior | E41: m2 | F41: =+Computo!K123 -> 656.8 | G41: =+'ANALISIS DE PRECIOS'!G1069 -> 1913.51 | H41: =+F41*G41 -> 1256793.4
C42: 4 | D42: Pintura Ventana | E42: m2
C43: 4.1 | D43: Pintura Puerta Ext | E43: m2
C44: 4.2 | D44: Pintura Puerta Int | E44: m2 | F44: =+Computo!K124 -> 1.827 | G44: =+'ANALISIS DE PRECIOS'!G1147 -> 1413.71 | H44: =+F44*G44 -> 2582.8482
C45: 4.3 | D45: Pintura Puerta Int | E45: m2 | F45: =+Computo!K125 -> 1.624 | G45: =+'ANALISIS DE PRECIOS'!G1147 -> 1413.71 | H45: =+F45*G45 -> 2295.865
C46: 4.4 | D46: CIELORRASO | I46: =+H47 -> 1016111.2
C47: 4.5 | D47: Cielorraso aplicado a la cal | E47: m2 | F47: =+Computo!L126 -> 212.5 | G47: =+'ANALISIS DE PRECIOS'!G1029 -> 4781.7 | H47: =+F47*G47 -> 1016111.2
C48: 4.6 | D48: CARPINTERIA METALICA | I48: =+H49+H54+H55+H50+H51+H52+H53 -> 235785.23
C49: 4.7 | D49: P1 Metalica | E49: cant | F49: =+Computo!L130 -> 4 | G49: 11682.87 | H49: =+F49*G49 -> 46731.48
C50: 4.8 | D50: V1 Metalica | E50: cant | F50: =+Computo!L131 -> 3 | G50: 16350 | H50: =+F50*G50 -> 49050
C51: 4.9 | D51: V2 Metalica | E51: cant | F51: =+Computo!L132 -> 2 | G51: 18190.75 | H51: =+F51*G51 -> 36381.5
C52: 5 | D52: V3 Metalica | E52: cant | F52: =+Computo!L133 -> 2 | G52: 16350 | H52: =+F52*G52 -> 32700
C53: 5.1 | D53: V4 Metalica | E53: cant | F53: =+Computo!L134 -> 3 | G53: 18190.75 | H53: =+F53*G53 -> 54572.25
C54: 5.2 | D54: V5 Metalica | E54: cant | F54: =+Computo!L135 -> 1 | G54: 16350 | H54: =+F54*G54 -> 16350
C55: 5.3 | D55: CARPINTERIA MADERA | I55: =H56+H57 -> 210926
C56: 5.4 | D56: P1 Madera | E56: cant | F56: =+Computo!L137 -> 4 | G56: 16350 | H56: =+F56*G56 -> 65400
C57: 5.5 | D57: P2 Madera | E57: cant | F57: =+Computo!L138 -> 8 | G57: 18190.75 | H57: =+F57*G57 -> 145526
C58: 5.6 | D58: VIDRIO | I58: =+H59+H60+H61+H62+H63 -> 44704.753
C59: 5.7 | D59: V1 | E59: m2 | F59: =+Computo!L140 -> 5.4 | G59: =+'ANALISIS DE PRECIOS'!G1419 -> 2486.36 | H59: =+F59*G59 -> 13426.344
C60: 5.8 | D60: V2 | E60: m2 | F60: =+Computo!L141 -> 4.8 | G60: =G59 -> 2486.36 | H60: =+F60*G60 -> 11934.528
C61: 5.9 | D61: V3 | E61: m2 | F61: =+Computo!L142 -> 3.36 | G61: =G59 -> 2486.36 | H61: =+F61*G61 -> 8354.1696
C62: 6 | D62: V4 | E62: m2 | F62: =+Computo!L143 -> 1.2 | G62: =G59 -> 2486.36 | H62: =+F62*G62 -> 2983.632
C63: 6.1 | D63: V5 | E63: m2 | F63: =+Computo!L144 -> 3.22 | G63: =G59 -> 2486.36 | H63: =+F63*G63 -> 8006.0792
D64: TOTAL COSTO - COSTO | I64: =SUM(I13:I59) -> 15286874 | J64: =SUM(J4:J59) -> 0
D65: COSTO - COSTO (A) | I65: =I64 -> 15286874
D66: GASTOS GENERALES | F66: 0.175 | I66: =I65*F66 -> 2675203
I67: =+I65+I66 -> 17962077
D68: BENEFICIO | F68: 0.1 | I68: =+I67*F68 -> 1796207.7
I69: =I65+I66+I68 -> 19758285
D70: IMPUESTOS | F70: 0.2375 | I70: =I69*F70 -> 4692592.6
D71: PRECIO TOTAL | I71: =I69+I70 -> 24450877
D73: COEFICIENTE DE IMPACTACION | I73: =I71/I65 -> 1.5994687
C75: SON PESOS: -------------------------------

Sheet Hoja1
